[
    {
        "entityId": 16461,
        "sku": "PLA-037-001",
        "stock": true,
        "prices": {
            "price": {
                "value": 24.04,
                "currencyCode": "USD"
            }
        },
        "variants": {
            "505": {
                "value_id": "2077",
                "label": "Mocha Brown"
            },
            "506": {
                "value_id": "2082",
                "label": "1/2\""
            },
            "507": {
                "value_id": "2084",
                "label": "12\" × 12\""
            }
        }
    },
    {
        "entityId": 16462,
        "sku": "PLA-037-002",
        "stock": true,
        "prices": {
            "price": {
                "value": 40.32,
                "currencyCode": "USD"
            }
        },
        "variants": {
            "505": {
                "value_id": "2077",
                "label": "Mocha Brown"
            },
            "506": {
                "value_id": "2082",
                "label": "1/2\""
            },
            "507": {
                "value_id": "2085",
                "label": "12\" × 24\""
            }
        }
    },
    {
        "entityId": 16463,
        "sku": "PLA-037-003",
        "stock": true,
        "prices": {
            "price": {
                "value": 69.44,
                "currencyCode": "USD"
            }
        },
        "variants": {
            "505": {
                "value_id": "2077",
                "label": "Mocha Brown"
            },
            "506": {
                "value_id": "2082",
                "label": "1/2\""
            },
            "507": {
                "value_id": "2086",
                "label": "12\" × 48\""
            }
        }
    },
    {
        "entityId": 16464,
        "sku": "PLA-037-004",
        "stock": true,
        "prices": {
            "price": {
                "value": 69.44,
                "currencyCode": "USD"
            }
        },
        "variants": {
            "505": {
                "value_id": "2077",
                "label": "Mocha Brown"
            },
            "506": {
                "value_id": "2082",
                "label": "1/2\""
            },
            "507": {
                "value_id": "2087",
                "label": "24\" × 24\""
            }
        }
    },
    {
        "entityId": 16465,
        "sku": "PLA-037-005",
        "stock": true,
        "prices": {
            "price": {
                "value": 97.4,
                "currencyCode": "USD"
            }
        },
        "variants": {
            "505": {
                "value_id": "2077",
                "label": "Mocha Brown"
            },
            "506": {
                "value_id": "2082",
                "label": "1/2\""
            },
            "507": {
                "value_id": "2088",
                "label": "24\" × 36\""
            }
        }
    },
    {
        "entityId": 16466,
        "sku": "PLA-037-006",
        "stock": true,
        "prices": {
            "price": {
                "value": 125.0,
                "currencyCode": "USD"
            }
        },
        "variants": {
            "505": {
                "value_id": "2077",
                "label": "Mocha Brown"
            },
            "506": {
                "value_id": "2082",
                "label": "1/2\""
            },
            "507": {
                "value_id": "2089",
                "label": "24\" × 48\""
            }
        }
    },
    {
        "entityId": 16467,
        "sku": "PLA-037-007",
        "stock": true,
        "prices": {
            "price": {
                "value": 32.49,
                "currencyCode": "USD"
            }
        },
        "variants": {
            "505": {
                "value_id": "2077",
                "label": "Mocha Brown"
            },
            "506": {
                "value_id": "2083",
                "label": "3/4\""
            },
            "507": {
                "value_id": "2084",
                "label": "12\" × 12\""
            }
        }
    },
    {
        "entityId": 16468,
        "sku": "PLA-037-008",
        "stock": true,
        "prices": {
            "price": {
                "value": 55.15,
                "currencyCode": "USD"
            }
        },
        "variants": {
            "505": {
                "value_id": "2077",
                "label": "Mocha Brown"
            },
            "506": {
                "value_id": "2083",
                "label": "3/4\""
            },
            "507": {
                "value_id": "2085",
                "label": "12\" × 24\""
            }
        }
    },
    {
        "entityId": 16469,
        "sku": "PLA-037-009",
        "stock": true,
        "prices": {
            "price": {
                "value": 97.4,
                "currencyCode": "USD"
            }
        },
        "variants": {
            "505": {
                "value_id": "2077",
                "label": "Mocha Brown"
            },
            "506": {
                "value_id": "2083",
                "label": "3/4\""
            },
            "507": {
                "value_id": "2086",
                "label": "12\" × 48\""
            }
        }
    },
    {
        "entityId": 16470,
        "sku": "PLA-037-010",
        "stock": true,
        "prices": {
            "price": {
                "value": 97.4,
                "currencyCode": "USD"
            }
        },
        "variants": {
            "505": {
                "value_id": "2077",
                "label": "Mocha Brown"
            },
            "506": {
                "value_id": "2083",
                "label": "3/4\""
            },
            "507": {
                "value_id": "2087",
                "label": "24\" × 24\""
            }
        }
    },
    {
        "entityId": 16471,
        "sku": "PLA-037-011",
        "stock": true,
        "prices": {
            "price": {
                "value": 140.63,
                "currencyCode": "USD"
            }
        },
        "variants": {
            "505": {
                "value_id": "2077",
                "label": "Mocha Brown"
            },
            "506": {
                "value_id": "2083",
                "label": "3/4\""
            },
            "507": {
                "value_id": "2088",
                "label": "24\" × 36\""
            }
        }
    },
    {
        "entityId": 16472,
        "sku": "PLA-037-012",
        "stock": true,
        "prices": {
            "price": {
                "value": 187.5,
                "currencyCode": "USD"
            }
        },
        "variants": {
            "505": {
                "value_id": "2077",
                "label": "Mocha Brown"
            },
            "506": {
                "value_id": "2083",
                "label": "3/4\""
            },
            "507": {
                "value_id": "2089",
                "label": "24\" × 48\""
            }
        }
    },
    {
        "entityId": 16473,
        "sku": "PLA-037-013",
        "stock": true,
        "prices": {
            "price": {
                "value": 24.04,
                "currencyCode": "USD"
            }
        },
        "variants": {
            "505": {
                "value_id": "2078",
                "label": "Nutmeg"
            },
            "506": {
                "value_id": "2082",
                "label": "1/2\""
            },
            "507": {
                "value_id": "2084",
                "label": "12\" × 12\""
            }
        }
    },
    {
        "entityId": 16474,
        "sku": "PLA-037-014",
        "stock": true,
        "prices": {
            "price": {
                "value": 40.32,
                "currencyCode": "USD"
            }
        },
        "variants": {
            "505": {
                "value_id": "2078",
                "label": "Nutmeg"
            },
            "506": {
                "value_id": "2082",
                "label": "1/2\""
            },
            "507": {
                "value_id": "2085",
                "label": "12\" × 24\""
            }
        }
    },
    {
        "entityId": 16475,
        "sku": "PLA-037-015",
        "stock": true,
        "prices": {
            "price": {
                "value": 69.44,
                "currencyCode": "USD"
            }
        },
        "variants": {
            "505": {
                "value_id": "2078",
                "label": "Nutmeg"
            },
            "506": {
                "value_id": "2082",
                "label": "1/2\""
            },
            "507": {
                "value_id": "2086",
                "label": "12\" × 48\""
            }
        }
    },
    {
        "entityId": 16476,
        "sku": "PLA-037-016",
        "stock": true,
        "prices": {
            "price": {
                "value": 69.44,
                "currencyCode": "USD"
            }
        },
        "variants": {
            "505": {
                "value_id": "2078",
                "label": "Nutmeg"
            },
            "506": {
                "value_id": "2082",
                "label": "1/2\""
            },
            "507": {
                "value_id": "2087",
                "label": "24\" × 24\""
            }
        }
    },
    {
        "entityId": 16477,
        "sku": "PLA-037-017",
        "stock": true,
        "prices": {
            "price": {
                "value": 97.4,
                "currencyCode": "USD"
            }
        },
        "variants": {
            "505": {
                "value_id": "2078",
                "label": "Nutmeg"
            },
            "506": {
                "value_id": "2082",
                "label": "1/2\""
            },
            "507": {
                "value_id": "2088",
                "label": "24\" × 36\""
            }
        }
    },
    {
        "entityId": 16478,
        "sku": "PLA-037-018",
        "stock": true,
        "prices": {
            "price": {
                "value": 125.0,
                "currencyCode": "USD"
            }
        },
        "variants": {
            "505": {
                "value_id": "2078",
                "label": "Nutmeg"
            },
            "506": {
                "value_id": "2082",
                "label": "1/2\""
            },
            "507": {
                "value_id": "2089",
                "label": "24\" × 48\""
            }
        }
    },
    {
        "entityId": 16479,
        "sku": "PLA-037-019",
        "stock": true,
        "prices": {
            "price": {
                "value": 32.49,
                "currencyCode": "USD"
            }
        },
        "variants": {
            "505": {
                "value_id": "2078",
                "label": "Nutmeg"
            },
            "506": {
                "value_id": "2083",
                "label": "3/4\""
            },
            "507": {
                "value_id": "2084",
                "label": "12\" × 12\""
            }
        }
    },
    {
        "entityId": 16480,
        "sku": "PLA-037-020",
        "stock": true,
        "prices": {
            "price": {
                "value": 55.15,
                "currencyCode": "USD"
            }
        },
        "variants": {
            "505": {
                "value_id": "2078",
                "label": "Nutmeg"
            },
            "506": {
                "value_id": "2083",
                "label": "3/4\""
            },
            "507": {
                "value_id": "2085",
                "label": "12\" × 24\""
            }
        }
    },
    {
        "entityId": 16481,
        "sku": "PLA-037-021",
        "stock": true,
        "prices": {
            "price": {
                "value": 97.4,
                "currencyCode": "USD"
            }
        },
        "variants": {
            "505": {
                "value_id": "2078",
                "label": "Nutmeg"
            },
            "506": {
                "value_id": "2083",
                "label": "3/4\""
            },
            "507": {
                "value_id": "2086",
                "label": "12\" × 48\""
            }
        }
    },
    {
        "entityId": 16482,
        "sku": "PLA-037-022",
        "stock": true,
        "prices": {
            "price": {
                "value": 97.4,
                "currencyCode": "USD"
            }
        },
        "variants": {
            "505": {
                "value_id": "2078",
                "label": "Nutmeg"
            },
            "506": {
                "value_id": "2083",
                "label": "3/4\""
            },
            "507": {
                "value_id": "2087",
                "label": "24\" × 24\""
            }
        }
    },
    {
        "entityId": 16483,
        "sku": "PLA-037-023",
        "stock": true,
        "prices": {
            "price": {
                "value": 140.63,
                "currencyCode": "USD"
            }
        },
        "variants": {
            "505": {
                "value_id": "2078",
                "label": "Nutmeg"
            },
            "506": {
                "value_id": "2083",
                "label": "3/4\""
            },
            "507": {
                "value_id": "2088",
                "label": "24\" × 36\""
            }
        }
    },
    {
        "entityId": 16484,
        "sku": "PLA-037-024",
        "stock": true,
        "prices": {
            "price": {
                "value": 187.5,
                "currencyCode": "USD"
            }
        },
        "variants": {
            "505": {
                "value_id": "2078",
                "label": "Nutmeg"
            },
            "506": {
                "value_id": "2083",
                "label": "3/4\""
            },
            "507": {
                "value_id": "2089",
                "label": "24\" × 48\""
            }
        }
    },
    {
        "entityId": 16485,
        "sku": "PLA-037-025",
        "stock": true,
        "prices": {
            "price": {
                "value": 24.04,
                "currencyCode": "USD"
            }
        },
        "variants": {
            "505": {
                "value_id": "2079",
                "label": "Indigo"
            },
            "506": {
                "value_id": "2082",
                "label": "1/2\""
            },
            "507": {
                "value_id": "2084",
                "label": "12\" × 12\""
            }
        }
    },
    {
        "entityId": 16486,
        "sku": "PLA-037-026",
        "stock": true,
        "prices": {
            "price": {
                "value": 40.32,
                "currencyCode": "USD"
            }
        },
        "variants": {
            "505": {
                "value_id": "2079",
                "label": "Indigo"
            },
            "506": {
                "value_id": "2082",
                "label": "1/2\""
            },
            "507": {
                "value_id": "2085",
                "label": "12\" × 24\""
            }
        }
    },
    {
        "entityId": 16487,
        "sku": "PLA-037-027",
        "stock": true,
        "prices": {
            "price": {
                "value": 69.44,
                "currencyCode": "USD"
            }
        },
        "variants": {
            "505": {
                "value_id": "2079",
                "label": "Indigo"
            },
            "506": {
                "value_id": "2082",
                "label": "1/2\""
            },
            "507": {
                "value_id": "2086",
                "label": "12\" × 48\""
            }
        }
    },
    {
        "entityId": 16488,
        "sku": "PLA-037-028",
        "stock": true,
        "prices": {
            "price": {
                "value": 69.44,
                "currencyCode": "USD"
            }
        },
        "variants": {
            "505": {
                "value_id": "2079",
                "label": "Indigo"
            },
            "506": {
                "value_id": "2082",
                "label": "1/2\""
            },
            "507": {
                "value_id": "2087",
                "label": "24\" × 24\""
            }
        }
    },
    {
        "entityId": 16489,
        "sku": "PLA-037-029",
        "stock": true,
        "prices": {
            "price": {
                "value": 97.4,
                "currencyCode": "USD"
            }
        },
        "variants": {
            "505": {
                "value_id": "2079",
                "label": "Indigo"
            },
            "506": {
                "value_id": "2082",
                "label": "1/2\""
            },
            "507": {
                "value_id": "2088",
                "label": "24\" × 36\""
            }
        }
    },
    {
        "entityId": 16490,
        "sku": "PLA-037-030",
        "stock": true,
        "prices": {
            "price": {
                "value": 125.0,
                "currencyCode": "USD"
            }
        },
        "variants": {
            "505": {
                "value_id": "2079",
                "label": "Indigo"
            },
            "506": {
                "value_id": "2082",
                "label": "1/2\""
            },
            "507": {
                "value_id": "2089",
                "label": "24\" × 48\""
            }
        }
    },
    {
        "entityId": 16491,
        "sku": "PLA-037-031",
        "stock": true,
        "prices": {
            "price": {
                "value": 32.49,
                "currencyCode": "USD"
            }
        },
        "variants": {
            "505": {
                "value_id": "2079",
                "label": "Indigo"
            },
            "506": {
                "value_id": "2083",
                "label": "3/4\""
            },
            "507": {
                "value_id": "2084",
                "label": "12\" × 12\""
            }
        }
    },
    {
        "entityId": 16492,
        "sku": "PLA-037-032",
        "stock": true,
        "prices": {
            "price": {
                "value": 55.15,
                "currencyCode": "USD"
            }
        },
        "variants": {
            "505": {
                "value_id": "2079",
                "label": "Indigo"
            },
            "506": {
                "value_id": "2083",
                "label": "3/4\""
            },
            "507": {
                "value_id": "2085",
                "label": "12\" × 24\""
            }
        }
    },
    {
        "entityId": 16493,
        "sku": "PLA-037-033",
        "stock": true,
        "prices": {
            "price": {
                "value": 97.4,
                "currencyCode": "USD"
            }
        },
        "variants": {
            "505": {
                "value_id": "2079",
                "label": "Indigo"
            },
            "506": {
                "value_id": "2083",
                "label": "3/4\""
            },
            "507": {
                "value_id": "2086",
                "label": "12\" × 48\""
            }
        }
    },
    {
        "entityId": 16494,
        "sku": "PLA-037-034",
        "stock": true,
        "prices": {
            "price": {
                "value": 97.4,
                "currencyCode": "USD"
            }
        },
        "variants": {
            "505": {
                "value_id": "2079",
                "label": "Indigo"
            },
            "506": {
                "value_id": "2083",
                "label": "3/4\""
            },
            "507": {
                "value_id": "2087",
                "label": "24\" × 24\""
            }
        }
    },
    {
        "entityId": 16495,
        "sku": "PLA-037-035",
        "stock": true,
        "prices": {
            "price": {
                "value": 140.63,
                "currencyCode": "USD"
            }
        },
        "variants": {
            "505": {
                "value_id": "2079",
                "label": "Indigo"
            },
            "506": {
                "value_id": "2083",
                "label": "3/4\""
            },
            "507": {
                "value_id": "2088",
                "label": "24\" × 36\""
            }
        }
    },
    {
        "entityId": 16496,
        "sku": "PLA-037-036",
        "stock": true,
        "prices": {
            "price": {
                "value": 187.5,
                "currencyCode": "USD"
            }
        },
        "variants": {
            "505": {
                "value_id": "2079",
                "label": "Indigo"
            },
            "506": {
                "value_id": "2083",
                "label": "3/4\""
            },
            "507": {
                "value_id": "2089",
                "label": "24\" × 48\""
            }
        }
    },
    {
        "entityId": 16497,
        "sku": "PLA-037-037",
        "stock": true,
        "prices": {
            "price": {
                "value": 24.04,
                "currencyCode": "USD"
            }
        },
        "variants": {
            "505": {
                "value_id": "2080",
                "label": "Charcoal Gray"
            },
            "506": {
                "value_id": "2082",
                "label": "1/2\""
            },
            "507": {
                "value_id": "2084",
                "label": "12\" × 12\""
            }
        }
    },
    {
        "entityId": 16498,
        "sku": "PLA-037-038",
        "stock": true,
        "prices": {
            "price": {
                "value": 40.32,
                "currencyCode": "USD"
            }
        },
        "variants": {
            "505": {
                "value_id": "2080",
                "label": "Charcoal Gray"
            },
            "506": {
                "value_id": "2082",
                "label": "1/2\""
            },
            "507": {
                "value_id": "2085",
                "label": "12\" × 24\""
            }
        }
    },
    {
        "entityId": 16499,
        "sku": "PLA-037-039",
        "stock": true,
        "prices": {
            "price": {
                "value": 69.44,
                "currencyCode": "USD"
            }
        },
        "variants": {
            "505": {
                "value_id": "2080",
                "label": "Charcoal Gray"
            },
            "506": {
                "value_id": "2082",
                "label": "1/2\""
            },
            "507": {
                "value_id": "2086",
                "label": "12\" × 48\""
            }
        }
    },
    {
        "entityId": 16500,
        "sku": "PLA-037-040",
        "stock": true,
        "prices": {
            "price": {
                "value": 69.44,
                "currencyCode": "USD"
            }
        },
        "variants": {
            "505": {
                "value_id": "2080",
                "label": "Charcoal Gray"
            },
            "506": {
                "value_id": "2082",
                "label": "1/2\""
            },
            "507": {
                "value_id": "2087",
                "label": "24\" × 24\""
            }
        }
    },
    {
        "entityId": 16501,
        "sku": "PLA-037-041",
        "stock": true,
        "prices": {
            "price": {
                "value": 97.4,
                "currencyCode": "USD"
            }
        },
        "variants": {
            "505": {
                "value_id": "2080",
                "label": "Charcoal Gray"
            },
            "506": {
                "value_id": "2082",
                "label": "1/2\""
            },
            "507": {
                "value_id": "2088",
                "label": "24\" × 36\""
            }
        }
    },
    {
        "entityId": 16502,
        "sku": "PLA-037-042",
        "stock": true,
        "prices": {
            "price": {
                "value": 125.0,
                "currencyCode": "USD"
            }
        },
        "variants": {
            "505": {
                "value_id": "2080",
                "label": "Charcoal Gray"
            },
            "506": {
                "value_id": "2082",
                "label": "1/2\""
            },
            "507": {
                "value_id": "2089",
                "label": "24\" × 48\""
            }
        }
    },
    {
        "entityId": 16503,
        "sku": "PLA-037-043",
        "stock": true,
        "prices": {
            "price": {
                "value": 32.49,
                "currencyCode": "USD"
            }
        },
        "variants": {
            "505": {
                "value_id": "2080",
                "label": "Charcoal Gray"
            },
            "506": {
                "value_id": "2083",
                "label": "3/4\""
            },
            "507": {
                "value_id": "2084",
                "label": "12\" × 12\""
            }
        }
    },
    {
        "entityId": 16504,
        "sku": "PLA-037-044",
        "stock": true,
        "prices": {
            "price": {
                "value": 55.15,
                "currencyCode": "USD"
            }
        },
        "variants": {
            "505": {
                "value_id": "2080",
                "label": "Charcoal Gray"
            },
            "506": {
                "value_id": "2083",
                "label": "3/4\""
            },
            "507": {
                "value_id": "2085",
                "label": "12\" × 24\""
            }
        }
    },
    {
        "entityId": 16505,
        "sku": "PLA-037-045",
        "stock": true,
        "prices": {
            "price": {
                "value": 97.4,
                "currencyCode": "USD"
            }
        },
        "variants": {
            "505": {
                "value_id": "2080",
                "label": "Charcoal Gray"
            },
            "506": {
                "value_id": "2083",
                "label": "3/4\""
            },
            "507": {
                "value_id": "2086",
                "label": "12\" × 48\""
            }
        }
    },
    {
        "entityId": 16506,
        "sku": "PLA-037-046",
        "stock": true,
        "prices": {
            "price": {
                "value": 97.4,
                "currencyCode": "USD"
            }
        },
        "variants": {
            "505": {
                "value_id": "2080",
                "label": "Charcoal Gray"
            },
            "506": {
                "value_id": "2083",
                "label": "3/4\""
            },
            "507": {
                "value_id": "2087",
                "label": "24\" × 24\""
            }
        }
    },
    {
        "entityId": 16507,
        "sku": "PLA-037-047",
        "stock": true,
        "prices": {
            "price": {
                "value": 140.63,
                "currencyCode": "USD"
            }
        },
        "variants": {
            "505": {
                "value_id": "2080",
                "label": "Charcoal Gray"
            },
            "506": {
                "value_id": "2083",
                "label": "3/4\""
            },
            "507": {
                "value_id": "2088",
                "label": "24\" × 36\""
            }
        }
    },
    {
        "entityId": 16508,
        "sku": "PLA-037-048",
        "stock": true,
        "prices": {
            "price": {
                "value": 187.5,
                "currencyCode": "USD"
            }
        },
        "variants": {
            "505": {
                "value_id": "2080",
                "label": "Charcoal Gray"
            },
            "506": {
                "value_id": "2083",
                "label": "3/4\""
            },
            "507": {
                "value_id": "2089",
                "label": "24\" × 48\""
            }
        }
    },
    {
        "entityId": 16509,
        "sku": "PLA-037-049",
        "stock": true,
        "prices": {
            "price": {
                "value": 24.04,
                "currencyCode": "USD"
            }
        },
        "variants": {
            "505": {
                "value_id": "2081",
                "label": "Slate Gray"
            },
            "506": {
                "value_id": "2082",
                "label": "1/2\""
            },
            "507": {
                "value_id": "2084",
                "label": "12\" × 12\""
            }
        }
    },
    {
        "entityId": 16510,
        "sku": "PLA-037-050",
        "stock": true,
        "prices": {
            "price": {
                "value": 40.32,
                "currencyCode": "USD"
            }
        },
        "variants": {
            "505": {
                "value_id": "2081",
                "label": "Slate Gray"
            },
            "506": {
                "value_id": "2082",
                "label": "1/2\""
            },
            "507": {
                "value_id": "2085",
                "label": "12\" × 24\""
            }
        }
    },
    {
        "entityId": 16511,
        "sku": "PLA-037-051",
        "stock": true,
        "prices": {
            "price": {
                "value": 69.44,
                "currencyCode": "USD"
            }
        },
        "variants": {
            "505": {
                "value_id": "2081",
                "label": "Slate Gray"
            },
            "506": {
                "value_id": "2082",
                "label": "1/2\""
            },
            "507": {
                "value_id": "2086",
                "label": "12\" × 48\""
            }
        }
    },
    {
        "entityId": 16512,
        "sku": "PLA-037-052",
        "stock": true,
        "prices": {
            "price": {
                "value": 69.44,
                "currencyCode": "USD"
            }
        },
        "variants": {
            "505": {
                "value_id": "2081",
                "label": "Slate Gray"
            },
            "506": {
                "value_id": "2082",
                "label": "1/2\""
            },
            "507": {
                "value_id": "2087",
                "label": "24\" × 24\""
            }
        }
    },
    {
        "entityId": 16513,
        "sku": "PLA-037-053",
        "stock": true,
        "prices": {
            "price": {
                "value": 97.4,
                "currencyCode": "USD"
            }
        },
        "variants": {
            "505": {
                "value_id": "2081",
                "label": "Slate Gray"
            },
            "506": {
                "value_id": "2082",
                "label": "1/2\""
            },
            "507": {
                "value_id": "2088",
                "label": "24\" × 36\""
            }
        }
    },
    {
        "entityId": 16514,
        "sku": "PLA-037-054",
        "stock": true,
        "prices": {
            "price": {
                "value": 125.0,
                "currencyCode": "USD"
            }
        },
        "variants": {
            "505": {
                "value_id": "2081",
                "label": "Slate Gray"
            },
            "506": {
                "value_id": "2082",
                "label": "1/2\""
            },
            "507": {
                "value_id": "2089",
                "label": "24\" × 48\""
            }
        }
    },
    {
        "entityId": 16515,
        "sku": "PLA-037-055",
        "stock": true,
        "prices": {
            "price": {
                "value": 32.49,
                "currencyCode": "USD"
            }
        },
        "variants": {
            "505": {
                "value_id": "2081",
                "label": "Slate Gray"
            },
            "506": {
                "value_id": "2083",
                "label": "3/4\""
            },
            "507": {
                "value_id": "2084",
                "label": "12\" × 12\""
            }
        }
    },
    {
        "entityId": 16516,
        "sku": "PLA-037-056",
        "stock": true,
        "prices": {
            "price": {
                "value": 55.15,
                "currencyCode": "USD"
            }
        },
        "variants": {
            "505": {
                "value_id": "2081",
                "label": "Slate Gray"
            },
            "506": {
                "value_id": "2083",
                "label": "3/4\""
            },
            "507": {
                "value_id": "2085",
                "label": "12\" × 24\""
            }
        }
    },
    {
        "entityId": 16517,
        "sku": "PLA-037-057",
        "stock": true,
        "prices": {
            "price": {
                "value": 97.4,
                "currencyCode": "USD"
            }
        },
        "variants": {
            "505": {
                "value_id": "2081",
                "label": "Slate Gray"
            },
            "506": {
                "value_id": "2083",
                "label": "3/4\""
            },
            "507": {
                "value_id": "2086",
                "label": "12\" × 48\""
            }
        }
    },
    {
        "entityId": 16518,
        "sku": "PLA-037-058",
        "stock": false,
        "prices": {
            "price": {
                "value": 97.4,
                "currencyCode": "USD"
            }
        },
        "variants": {
            "505": {
                "value_id": "2081",
                "label": "Slate Gray"
            },
            "506": {
                "value_id": "2083",
                "label": "3/4\""
            },
            "507": {
                "value_id": "2087",
                "label": "24\" × 24\""
            }
        }
    },
    {
        "entityId": 16519,
        "sku": "PLA-037-059",
        "stock": true,
        "prices": {
            "price": {
                "value": 140.63,
                "currencyCode": "USD"
            }
        },
        "variants": {
            "505": {
                "value_id": "2081",
                "label": "Slate Gray"
            },
            "506": {
                "value_id": "2083",
                "label": "3/4\""
            },
            "507": {
                "value_id": "2088",
                "label": "24\" × 36\""
            }
        }
    },
    {
        "entityId": 16520,
        "sku": "PLA-037-060",
        "stock": true,
        "prices": {
            "price": {
                "value": 187.5,
                "currencyCode": "USD"
            }
        },
        "variants": {
            "505": {
                "value_id": "2081",
                "label": "Slate Gray"
            },
            "506": {
                "value_id": "2083",
                "label": "3/4\""
            },
            "507": {
                "value_id": "2089",
                "label": "24\" × 48\""
            }
        }
    },
    {
        "entityId": 17871,
        "sku": "PLA-037-A01",
        "stock": true,
        "prices": {
            "price": {
                "value": 416.67,
                "currencyCode": "USD"
            }
        },
        "variants": {
            "505": {
                "value_id": "2077",
                "label": "Mocha Brown"
            },
            "506": {
                "value_id": "2082",
                "label": "1/2\""
            },
            "507": {
                "value_id": "2345",
                "label": "48\" × 96\""
            }
        }
    },
    {
        "entityId": 17872,
        "sku": "PLA-037-A02",
        "stock": true,
        "prices": {
            "price": {
                "value": 625.0,
                "currencyCode": "USD"
            }
        },
        "variants": {
            "505": {
                "value_id": "2077",
                "label": "Mocha Brown"
            },
            "506": {
                "value_id": "2083",
                "label": "3/4\""
            },
            "507": {
                "value_id": "2345",
                "label": "48\" × 96\""
            }
        }
    },
    {
        "entityId": 17873,
        "sku": "PLA-037-A03",
        "stock": true,
        "prices": {
            "price": {
                "value": 416.67,
                "currencyCode": "USD"
            }
        },
        "variants": {
            "505": {
                "value_id": "2078",
                "label": "Nutmeg"
            },
            "506": {
                "value_id": "2082",
                "label": "1/2\""
            },
            "507": {
                "value_id": "2345",
                "label": "48\" × 96\""
            }
        }
    },
    {
        "entityId": 17874,
        "sku": "PLA-037-A04",
        "stock": true,
        "prices": {
            "price": {
                "value": 625.0,
                "currencyCode": "USD"
            }
        },
        "variants": {
            "505": {
                "value_id": "2078",
                "label": "Nutmeg"
            },
            "506": {
                "value_id": "2083",
                "label": "3/4\""
            },
            "507": {
                "value_id": "2345",
                "label": "48\" × 96\""
            }
        }
    },
    {
        "entityId": 17875,
        "sku": "PLA-037-A05",
        "stock": true,
        "prices": {
            "price": {
                "value": 416.67,
                "currencyCode": "USD"
            }
        },
        "variants": {
            "505": {
                "value_id": "2079",
                "label": "Indigo"
            },
            "506": {
                "value_id": "2082",
                "label": "1/2\""
            },
            "507": {
                "value_id": "2345",
                "label": "48\" × 96\""
            }
        }
    },
    {
        "entityId": 17876,
        "sku": "PLA-037-A06",
        "stock": true,
        "prices": {
            "price": {
                "value": 625.0,
                "currencyCode": "USD"
            }
        },
        "variants": {
            "505": {
                "value_id": "2079",
                "label": "Indigo"
            },
            "506": {
                "value_id": "2083",
                "label": "3/4\""
            },
            "507": {
                "value_id": "2345",
                "label": "48\" × 96\""
            }
        }
    },
    {
        "entityId": 17877,
        "sku": "PLA-037-A07",
        "stock": true,
        "prices": {
            "price": {
                "value": 416.67,
                "currencyCode": "USD"
            }
        },
        "variants": {
            "505": {
                "value_id": "2080",
                "label": "Charcoal Gray"
            },
            "506": {
                "value_id": "2082",
                "label": "1/2\""
            },
            "507": {
                "value_id": "2345",
                "label": "48\" × 96\""
            }
        }
    },
    {
        "entityId": 17878,
        "sku": "PLA-037-A08",
        "stock": true,
        "prices": {
            "price": {
                "value": 625.0,
                "currencyCode": "USD"
            }
        },
        "variants": {
            "505": {
                "value_id": "2080",
                "label": "Charcoal Gray"
            },
            "506": {
                "value_id": "2083",
                "label": "3/4\""
            },
            "507": {
                "value_id": "2345",
                "label": "48\" × 96\""
            }
        }
    },
    {
        "entityId": 17879,
        "sku": "PLA-037-A09",
        "stock": true,
        "prices": {
            "price": {
                "value": 416.67,
                "currencyCode": "USD"
            }
        },
        "variants": {
            "505": {
                "value_id": "2081",
                "label": "Slate Gray"
            },
            "506": {
                "value_id": "2082",
                "label": "1/2\""
            },
            "507": {
                "value_id": "2345",
                "label": "48\" × 96\""
            }
        }
    },
    {
        "entityId": 17880,
        "sku": "PLA-037-A10",
        "stock": false,
        "prices": {
            "price": {
                "value": 625.0,
                "currencyCode": "USD"
            }
        },
        "variants": {
            "505": {
                "value_id": "2081",
                "label": "Slate Gray"
            },
            "506": {
                "value_id": "2083",
                "label": "3/4\""
            },
            "507": {
                "value_id": "2345",
                "label": "48\" × 96\""
            }
        }
    }
]